README.txt
buildout.cfg
setup.cfg
setup.py
test-plone-3.3.x.cfg
test-plone-4.0.x.cfg
docs/HISTORY.txt
src/README.txt
src/collective/__init__.py
src/collective.synchronisedworkflow.egg-info/PKG-INFO
src/collective.synchronisedworkflow.egg-info/SOURCES.txt
src/collective.synchronisedworkflow.egg-info/dependency_links.txt
src/collective.synchronisedworkflow.egg-info/entry_points.txt
src/collective.synchronisedworkflow.egg-info/namespace_packages.txt
src/collective.synchronisedworkflow.egg-info/not-zip-safe
src/collective.synchronisedworkflow.egg-info/requires.txt
src/collective.synchronisedworkflow.egg-info/top_level.txt
src/collective/synchronisedworkflow/README.txt
src/collective/synchronisedworkflow/__init__.py
src/collective/synchronisedworkflow/configure.zcml
src/collective/synchronisedworkflow/patches.py
src/collective/synchronisedworkflow/utils.py
src/collective/synchronisedworkflow/tests/__init__.py
src/collective/synchronisedworkflow/tests/base.py
src/collective/synchronisedworkflow/tests/test_states_equal.py