Metadata-Version: 1.0
Name: collective.synchronisedworkflow
Version: 1.0
Summary: Causes translated Plone content to share the same workflow state.
Home-page: UNKNOWN
Author: Matthew Wilkes
Author-email: matthew@circulartriangle.eu
License: GPL
Platform: UNKNOWN
Classifier: Programming Language :: Python
Classifier: Topic :: Software Development :: Libraries :: Python Modules
Classifier: Framework :: Plone
Classifier: Framework :: Zope2
Classifier: Topic :: Software Development :: Internationalization
Classifier: Intended Audience :: Developers
Classifier: Intended Audience :: End Users/Desktop
Classifier: License :: OSI Approved :: GNU General Public License (GPL)
Classifier: Development Status :: 4 - Beta
